abhi_git/nevan_fsm/Count.v
module Count(clk, rst, count); 
    //Define inputs here
    input clk; 

    input rst; 

    //Define outputs here
    output reg [2:0] count;

    //Define Registers
    reg [2:0] seven_counter;
    reg [1:0] three_counter;

    //Define States
    parameter s_idle = 0, s_count = 1; 

    reg [1:0] state, state_next;

    reg isDone; 

    //Define Logic
    always @(posedge clk) begin
        state = state_next;
    end

    always @(posedge clk) begin
        case (state)
            s_idle: begin
                if (rst == 1) begin 
                    state_next = s_idle; 
                end else if (rst == 0 && isDone == 0) begin
                    state_next = s_count; 
                    seven_counter = 0; 
                    three_counter = 0; //Possibly look at this
		    count = 0;            
                end else begin
                    state_next = s_idle;
                end

            end

        s_count: begin 
            if (rst == 1) begin 
                state_next = s_idle; 
            end else if (rst == 0) begin
                
                count = seven_counter; 

                if (three_counter < 3) begin 
                    if (seven_counter < 7) begin 
                        seven_counter = seven_counter + 1;
                        state_next = s_count;
                    end else begin
                        seven_counter = 0; 
                        three_counter = three_counter + 1;
                        state_next = s_count;
                    end
                end else begin 
                    count = 7; 
                    state_next = s_idle; 
                    isDone = 1; 
                end
            end
        end


            default begin 
                state_next = s_idle; 
                isDone = 0; 
            end
        endcase 

    end 

    

endmodule

abhi_git/nevan_fsm/tb_count.v
`timescale 1ns/1ns
`include "Count.v"
module tb_count();  

    //Define inputs as reg
    reg clk; 
    reg rst; 


    //Define outputs as wire
    wire [2:0] count; 

    //Define moudle
    Count counter(
        .clk(clk), 
        .rst(rst), 
        .count(count)
    );

    //Define clk

    always begin 
        clk = 0; 
        #5;
        clk = 1; 
        #5;
    end



    initial begin 
        $dumpvars(0, tb_count);

        rst = 1; 
        repeat (4) @(posedge clk); //start at not counting
				   //see if it waits the right amount of time

	rst = 0;
	repeat (10) @(posedge clk); //see if it counts to 7 then 3

	rst = 1;
	repeat (2) @(posedge clk); //interrupt counting with 
				   //another reset. See if it works

	rst = 0;
	repeat(30) @(posedge clk); //let it run

        $finish; 
    end


    //Logic

endmodule

abhi_git/nevan_fsm/dump.vcd
$date
	Tue Sep  2 14:35:24 2025
$end
$version
	Icarus Verilog
$end
$timescale
	1ns
$end
$scope module tb_count $end
$var wire 3 ! count [2:0] $end
$var reg 1 " clk $end
$var reg 1 # rst $end
$scope module counter $end
$var wire 1 " clk $end
$var wire 1 # rst $end
$var parameter 32 $ s_count $end
$var parameter 32 % s_idle $end
$var reg 3 & count [2:0] $end
$var reg 1 ' isDone $end
$var reg 3 ( seven_counter [2:0] $end
$var reg 2 ) state [1:0] $end
$var reg 2 * state_next [1:0] $end
$var reg 2 + three_counter [1:0] $end
$upscope $end
$upscope $end
$enddefinitions $end
$comment Show the parameter values. $end
$dumpall
b0 %
b1 $
$end
#0
$dumpvars
bx +
bx *
bx )
bx (
x'
bx &
1#
0"
bx !
$end
#5
b0 )
0'
b0 *
1"
#10
0"
#15
1"
#20
0"
#25
1"
#30
0"
#35
0#
1"
#40
0"
#45
b1 )
b0 +
b0 (
b1 *
1"
#50
0"
#55
b1 (
b0 !
b0 &
1"
#60
0"
#65
b10 (
b1 !
b1 &
1"
#70
0"
#75
b11 (
b10 !
b10 &
1"
#80
0"
#85
b100 (
b11 !
b11 &
1"
#90
0"
#95
b101 (
b100 !
b100 &
1"
#100
0"
#105
b110 (
b101 !
b101 &
1"
#110
0"
#115
b111 (
b110 !
b110 &
1"
#120
0"
#125
b1 +
b0 (
b111 !
b111 &
1"
#130
0"
#135
1#
b1 (
b0 !
b0 &
1"
#140
0"
#145
b0 )
b0 *
1"
#150
0"
#155
0#
1"
#160
0"
#165
b1 )
b0 +
b0 (
b1 *
1"
#170
0"
#175
b1 (
1"
#180
0"
#185
b10 (
b1 !
b1 &
1"
#190
0"
#195
b11 (
b10 !
b10 &
1"
#200
0"
#205
b100 (
b11 !
b11 &
1"
#210
0"
#215
b101 (
b100 !
b100 &
1"
#220
0"
#225
b110 (
b101 !
b101 &
1"
#230
0"
#235
b111 (
b110 !
b110 &
1"
#240
0"
#245
b1 +
b0 (
b111 !
b111 &
1"
#250
0"
#255
b1 (
b0 !
b0 &
1"
#260
0"
#265
b10 (
b1 !
b1 &
1"
#270
0"
#275
b11 (
b10 !
b10 &
1"
#280
0"
#285
b100 (
b11 !
b11 &
1"
#290
0"
#295
b101 (
b100 !
b100 &
1"
#300
0"
#305
b110 (
b101 !
b101 &
1"
#310
0"
#315
b111 (
b110 !
b110 &
1"
#320
0"
#325
b10 +
b0 (
b111 !
b111 &
1"
#330
0"
#335
b1 (
b0 !
b0 &
1"
#340
0"
#345
b10 (
b1 !
b1 &
1"
#350
0"
#355
b11 (
b10 !
b10 &
1"
#360
0"
#365
b100 (
b11 !
b11 &
1"
#370
0"
#375
b101 (
b100 !
b100 &
1"
#380
0"
#385
b110 (
b101 !
b101 &
1"
#390
0"
#395
b111 (
b110 !
b110 &
1"
#400
0"
#405
b11 +
b0 (
b111 !
b111 &
1"
#410
0"
#415
1'
b0 *
b111 !
b111 &
1"
#420
0"
#425
b0 )
b111 !
b111 &
1"
